oknrerun/__init__.py
oknrerun/gazefilters.json
oknrerun/okn_detection_rule.json
oknrerun/okndetector.gaze.config
oknrerun/oknrerun.py
oknrerun/oknserver_graph_plot_config.json
oknrerun/opm_detector_config.json
oknrerun/ui.py
oknrerun-1.1.1.dist-info/licenses/LICENSE
oknrerun-1.1.1.dist-info/METADATA
oknrerun-1.1.1.dist-info/WHEEL
oknrerun-1.1.1.dist-info/entry_points.txt
oknrerun-1.1.1.dist-info/top_level.txt
oknrerun-1.1.1.dist-info/RECORD
