Metadata-Version: 2.4
Name: oknrerun
Version: 1.1.1
Summary: Python program to rerun eye health diagnostic group's recording data
Author-email: Zaw Lin Tun <zawlintun1511@gmail.com>
Project-URL: Homepage, https://github.com/jtur044/oknrerun
Project-URL: Bug Tracker, https://github.com/jtur044/oknrerun/issues
Classifier: Programming Language :: Python :: 3
Classifier: License :: OSI Approved :: Apache Software License
Classifier: Operating System :: OS Independent
License-File: LICENSE
Requires-Dist: setuptools>=61.0
Requires-Dist: numpy
Requires-Dist: commentjson
Requires-Dist: scipy
Requires-Dist: matplotlib
Requires-Dist: ehdg_tools>=4.6.3
Requires-Dist: ehdg_pupil_detector
Requires-Dist: okntool
Requires-Dist: opencv-python
Dynamic: license-file
